cadbuildr/__init__.py
cadbuildr/stdlib/__init__.py
cadbuildr/stdlib/fasterners/nuts/hex_din934_part.py
cadbuildr/stdlib/fasterners/screws_and_bolts/__init__.py
cadbuildr/stdlib/fasterners/screws_and_bolts/din912_part.py
cadbuildr/stdlib/fasterners/threaded_rods/base_part.py
cadbuildr/stdlib/fasterners/washers/din125_part.py
cadbuildr/stdlib/power_transmission/shafts/base_part.py
cadbuildr_stdlib-0.0.0.2.dist-info/LICENSE
cadbuildr_stdlib-0.0.0.2.dist-info/METADATA
cadbuildr_stdlib-0.0.0.2.dist-info/WHEEL
cadbuildr_stdlib-0.0.0.2.dist-info/RECORD
