Metadata-Version: 2.1
Name: cadbuildr-stdlib
Version: 0.0.0.2
Summary: Standard library for cadbuildr with tools, parts, assemblies built on top of foundation
Author: Cadbuildr Team
Requires-Python: >=3.10,<4.0
Classifier: Programming Language :: Python :: 3
Classifier: Programming Language :: Python :: 3.10
Classifier: Programming Language :: Python :: 3.11
Classifier: Programming Language :: Python :: 3.12
Requires-Dist: cadbuildr-foundation (>=0.0.0.13,<0.0.1.0)
